bdf/__init__.py
bdf/bdf.py
bdf/exceptions.py
business_dataset_formatter-0.0.1.dist-info/LICENSE
business_dataset_formatter-0.0.1.dist-info/METADATA
business_dataset_formatter-0.0.1.dist-info/WHEEL
business_dataset_formatter-0.0.1.dist-info/top_level.txt
business_dataset_formatter-0.0.1.dist-info/RECORD
