Metadata-Version: 2.1
Name: business-dataset-formatter
Version: 0.0.1
Summary: A simple dataset formatter based on business days and weekends.
Home-page: https://github.com/evtlucas/business_dataset_formatter
Author: Everton Lucas
Author-email: evtlucas@gmail.com
License: UNKNOWN
Platform: UNKNOWN
Classifier: Programming Language :: Python :: 3
Classifier: License :: OSI Approved :: MIT License
Classifier: Operating System :: OS Independent
Requires-Python: >=3.6
